README.md
setup.cfg
setup.py
paynet/__init__.py
paynet/admin.py
paynet/apps.py
paynet/exceptions.py
paynet/models.py
paynet/serializers.py
paynet/urls.py
paynet/utils.py
paynet/views.py
paynet/migrations/__init__.py
paynet_pkg.egg-info/PKG-INFO
paynet_pkg.egg-info/SOURCES.txt
paynet_pkg.egg-info/dependency_links.txt
paynet_pkg.egg-info/requires.txt
paynet_pkg.egg-info/top_level.txt