Metadata-Version: 2.1
Name: paynet-pkg
Version: 0.3
Home-page: https://github.com/Muhammadali-Akbarov/paynet-pkg
Author: Muhammadali Akbarov
Author-email: muhammadali17abc@gmail.com
License: MIT
Keywords: paynet,paynet-merchant,paynet-pkg,paynet-api,paynet-python-integration,paynet-integration,paynet-python,paynet-gateway,paynet-payment,paynet-payment-gateway,paynet-integration-python,paynet-api-client,paynet-django,paynet-rest-api
Requires-Dist: requests==2.*
Requires-Dist: dataclasses==0.*; python_version < "3.7"
Requires-Dist: djangorestframework==3.*
